datasette_remove_database/__init__.py
datasette_remove_database-0.1a2.dist-info/METADATA
datasette_remove_database-0.1a2.dist-info/WHEEL
datasette_remove_database-0.1a2.dist-info/entry_points.txt
datasette_remove_database-0.1a2.dist-info/top_level.txt
datasette_remove_database-0.1a2.dist-info/RECORD
