Metadata-Version: 2.4
Name: datasette-remove-database
Version: 0.1a2
Summary: Remove a database from Datasette
Author: Simon Willison
License-Expression: Apache-2.0
Project-URL: Homepage, https://github.com/datasette/datasette-remove-database
Project-URL: Changelog, https://github.com/datasette/datasette-remove-database/releases
Project-URL: Issues, https://github.com/datasette/datasette-remove-database/issues
Project-URL: CI, https://github.com/datasette/datasette-remove-database/actions
Classifier: Framework :: Datasette
Requires-Python: >=3.10
Requires-Dist: datasette>=1.0a21
Provides-Extra: test
Requires-Dist: pytest; extra == "test"
Requires-Dist: pytest-asyncio; extra == "test"
